han/__init__.py
han/token.py
han/vocabulary.py
han/encode/__init__.py
han/encode/document.py
han/encode/sentence.py
han/example/__init__.py
han/example/ag_news.py
han/example/document.py
han/example/model.py
han/example/sentence.py
han/model/__init__.py
han/model/attention.py
han/model/document.py
han/model/sentence.py
hierarchical_attention_networks-0.0.3.dist-info/LICENSE
hierarchical_attention_networks-0.0.3.dist-info/METADATA
hierarchical_attention_networks-0.0.3.dist-info/WHEEL
hierarchical_attention_networks-0.0.3.dist-info/entry_points.txt
hierarchical_attention_networks-0.0.3.dist-info/top_level.txt
hierarchical_attention_networks-0.0.3.dist-info/RECORD
